JasonUtils/ConstantEstimator.py
JasonUtils/Datasets.py
JasonUtils/Help.py
JasonUtils/Results.py
JasonUtils/TicToc.py
JasonUtils/Utils.py
JasonUtils/__init__.py
JasonUtils-1.0.6.dist-info/LICENSE
JasonUtils-1.0.6.dist-info/METADATA
JasonUtils-1.0.6.dist-info/WHEEL
JasonUtils-1.0.6.dist-info/top_level.txt
JasonUtils-1.0.6.dist-info/RECORD
